Workbook

Sheet INVESTIMENTO INICIAL
A1: Produto | B1: Quantidade | C1: Valor unitário | D1: Total | E1: Prioridade
A2: Freezer horizontal 300L | B2: 1 | C2: 2200 | D2: =B2*C2 -> 2200 | E2: Essencial
A3: Geladeira duplex (se não houver disponível em casa) | B3: 1 | C3: 2500 | D3: =B3*C3 -> 2500 | E3: Essencial
A4: Batedeira planetária 5L | B4: 1 | C4: 800 | D4: =B4*C4 -> 800 | E4: Essencial
A5: Liquidificador profissional | B5: 1 | C5: 450 | D5: =B5*C5 -> 450 | E5: Essencial
A6: Forno elétrico de bancada 45L | B6: 1 | C6: 900 | D6: =B6*C6 -> 900 | E6: Essencial
A7: Assadeiras antiaderentes (kit com 5) | B7: 1 | C7: 250 | D7: =B7*C7 -> 250 | E7: Essencial
A8: Utensílios diversos (bowls, espátulas, facas) | B8: 1 | C8: 300 | D8: =B8*C8 -> 300 | E8: Essencial
A9: Balança digital de precisão (até 5kg) | B9: 1 | C9: 120 | D9: =B9*C9 -> 120 | E9: Essencial
A10: Seladora de embalagens | B10: 1 | C10: 250 | D10: =B10*C10 -> 250 | E10: Essencial
A11: Bancada de produção em inox | B11: 1 | C11: 900 | D11: =B11*C11 -> 900 | E11: Essencial
A12: Embalagens iniciais (potes 200ml + sacos kraft) | B12: 1 | C12: 500 | D12: =B12*C12 -> 500 | E12: Essencial
A13: Etiquetas personalizadas (rolo, 1000un) | B13: 1 | C13: 150 | D13: =B13*C13 -> 150 | E13: Essencial
... A21: Identidade visual profissional (logo, papelaria) | B21: 1 | C21: 800 | D21: =B21*C21 -> 800 | E21: Futuro crescimento
A22: TOTAL GERAL | D22: =SUM(D2:D21) -> 28390
A24: Nota: valores em azul são estimativas de mercado (2026) e podem ser editados conforme cotação real. Item 'Geladeira duplex' pode ser removido do total essencial se a residência já tiver uma disponível para uso exclusivo do negócio.

Sheet CUSTO DOS PRODUTOS
A1: Produto | B1: Ingredientes | C1: Custo receita | D1: Quantidade produzida | E1: Custo unitário
A2: Pão recheado frango + queijo | B2: Farinha, fermento, açúcar, sal, ovos, leite, manteiga, frango desfiado, queijo muçarela, requeijão | C2: 40.47 | D2: 20 | E2: =C2/D2 -> 2.0235
A3: Pão recheado calabresa + queijo | B3: Farinha, fermento, açúcar, sal, ovos, leite, manteiga, calabresa, queijo muçarela, cebola | C3: 29.67 | D3: 20 | E3: =C3/D3 -> 1.4835
A4: Pão recheado presunto + queijo | B4: Farinha, fermento, açúcar, sal, ovos, leite, manteiga, presunto, queijo muçarela | C4: 29.87 | D4: 20 | E4: =C4/D4 -> 1.4935
A5: Pão recheado rúcula + queijo | B5: Farinha, fermento, açúcar, sal, ovos, leite, manteiga, rúcula, queijo/ricota, tomate seco | C5: 35.47 | D5: 20 | E5: =C5/D5 -> 1.7735
A6: Mousse de chocolate | B6: Chocolate meio amargo, creme de leite, leite condensado, claras de ovo | C6: 30 | D6: 10 | E6: =C6/D6 -> 3
A7: Mousse de maracujá | B7: Suco concentrado de maracujá, leite condensado, creme de leite, gelatina incolor | C7: 23 | D7: 10 | E7: =C7/D7 -> 2.3
A8: Mousse de limão | B8: Suco e raspas de limão, leite condensado, creme de leite, gelatina incolor | C8: 20 | D8: 10 | E8: =C8/D8 -> 2
A9: Banoffee no pote | B9: Bolacha, manteiga, doce de leite, banana, chantilly, chocolate em raspas | C9: 27.75 | D9: 8 | E9: =C9/D9 -> 3.46875
A10: Pavê no pote | B10: Biscoito champanhe, leite condensado, leite, creme de leite, chocolate em pó | C10: 24 | D10: 10 | E10: =C10/D10 -> 2.4
A12: Nota: 'Custo receita' considera apenas ingredientes (massa + recheio ou creme), sem embalagem. O custo de embalagem é somado na aba PRECIFICAÇÃO.

Sheet PRECIFICAÇÃO
A1: Produto | B1: Custo | C1: Margem desejada | D1: Preço venda | E1: Lucro
A2: Pão recheado frango + queijo | B2: ='CUSTO DOS PRODUTOS'!E2+0.4 -> 2.4235 | C2: 0.6543 | D2: =B2/(1-C2) -> 7.0104137 | E2: =D2-B2 -> 4.5869137
A3: Pão recheado calabresa + queijo | B3: ='CUSTO DOS PRODUTOS'!E3+0.4 -> 1.8835 | C3: 0.7108 | D3: =B3/(1-C3) -> 6.5127939 | E3: =D3-B3 -> 4.6292939
A4: Pão recheado presunto + queijo | B4: ='CUSTO DOS PRODUTOS'!E4+0.4 -> 1.8935 | C4: 0.7092 | D4: =B4/(1-C4) -> 6.511348 | E4: =D4-B4 -> 4.617848
A5: Pão recheado rúcula + queijo | B5: ='CUSTO DOS PRODUTOS'!E5+0.4 -> 2.1735 | C5: 0.7107 | D5: =B5/(1-C5) -> 7.5129623 | E5: =D5-B5 -> 5.3394623
A6: Mousse de chocolate | B6: ='CUSTO DOS PRODUTOS'!E6+1.2 -> 4.2 | C6: 0.65 | D6: =B6/(1-C6) -> 12 | E6: =D6-B6 -> 7.8
A7: Mousse de maracujá | B7: ='CUSTO DOS PRODUTOS'!E7+1.2 -> 3.5 | C7: 0.6818 | D7: =B7/(1-C7) -> 10.999371 | E7: =D7-B7 -> 7.4993715
A8: Mousse de limão | B8: ='CUSTO DOS PRODUTOS'!E8+1.2 -> 3.2 | C8: 0.7091 | D8: =B8/(1-C8) -> 11.000344 | E8: =D8-B8 -> 7.8003438
A9: Banoffee no pote | B9: ='CUSTO DOS PRODUTOS'!E9+1.5 -> 4.96875 | C9: 0.645 | D9: =B9/(1-C9) -> 13.996479 | E9: =D9-B9 -> 9.0277289
A10: Pavê no pote | B10: ='CUSTO DOS PRODUTOS'!E10+1.2 -> 3.6 | C10: 0.6727 | D10: =B10/(1-C10) -> 10.999083 | E10: =D10-B10 -> 7.3990834
A12: Como usar: edite a 'Margem desejada' (célula amarela) para simular preços. 'Preço venda' recalcula automaticamente como Custo / (1 - Margem desejada).

Sheet CONTROLE DIÁRIO
A1: Data | B1: Produto vendido | C1: Quantidade | D1: Receita | E1: Custos | F1: Lucro
A2: 46244 | B2: Pão recheado frango + queijo (10 un) | C2: 10 | D2: 70 | E2: 24.2 | F2: =D2-E2 -> 45.8
F3: =D3-E3 -> 0
F4: =D4-E4 -> 0
F5: =D5-E5 -> 0
F6: =D6-E6 -> 0
F7: =D7-E7 -> 0
F8: =D8-E8 -> 0
F9: =D9-E9 -> 0
F10: =D10-E10 -> 0
F11: =D11-E11 -> 0
F12: =D12-E12 -> 0
F13: =D13-E13 -> 0
F14: =D14-E14 -> 0
... F32: =D32-E32 -> 0
A34: TOTAL | C34: =SUM(C2:C33) -> 10 | D34: =SUM(D2:D33) -> 70 | E34: =SUM(E2:E33) -> 24.2 | F34: =SUM(F2:F33) -> 45.8
A36: Linha 2 (amarela) é um exemplo de preenchimento. Preencha Data, Produto vendido, Quantidade, Receita e Custos a cada venda — a coluna Lucro calcula sozinha.

Sheet DRE SIMPLIFICADA
A1: Item | B1: Mês 1 | C1: Mês 2 | D1: Mês 3 | E1: Mês 4 | F1: Mês 5 | G1: Mês 6 | H1: Mês 7 | I1: Mês 8 | J1: Mês 9 | K1: Mês 10 | L1: Mês 11 | M1: Mês 12 | N1: Total Ano
A2: Receita bruta | B2: 1350 | C2: 2000 | D2: 2950 | E2: 3700 | F2: 4450 | G2: 5200 | H2: 5750 | I2: 6300 | J2: 6850 | K2: 7400 | L2: 7900 | M2: 8400 | N2: =SUM(B2:M2) -> 62250
A3: (-) Matéria-prima | B3: 429 | C3: 608 | D3: 858 | E3: 1053 | F3: 1248 | G3: 1443 | H3: 1583 | I3: 1716 | J3: 1856 | K3: 1989 | L3: 2106 | M3: 2223 | N3: =SUM(B3:M3) -> 17112
A4: (-) Embalagens | B4: 66 | C4: 94 | D4: 132 | E4: 162 | F4: 192 | G4: 222 | H4: 244 | I4: 264 | J4: 286 | K4: 306 | L4: 324 | M4: 342 | N4: =SUM(B4:M4) -> 2634
A5: (-) Energia | B5: 33 | C5: 47 | D5: 66 | E5: 81 | F5: 96 | G5: 111 | H5: 122 | I5: 132 | J5: 143 | K5: 153 | L5: 162 | M5: 171 | N5: =SUM(B5:M5) -> 1317
A6: (-) Outros custos | B6: 22 | C6: 31 | D6: 44 | E6: 54 | F6: 64 | G6: 74 | H6: 81 | I6: 88 | J6: 95 | K6: 102 | L6: 108 | M6: 114 | N6: =SUM(B6:M6) -> 877
A7: Lucro líquido | B7: =B2-SUM(B3:B6) -> 800 | C7: =C2-SUM(C3:C6) -> 1220 | D7: =D2-SUM(D3:D6) -> 1850 | E7: =E2-SUM(E3:E6) -> 2350 | F7: =F2-SUM(F3:F6) -> 2850 | G7: =G2-SUM(G3:G6) -> 3350 | H7: =H2-SUM(H3:H6) -> 3720 | I7: =I2-SUM(I3:I6) -> 4100 | ... N7: =N2-SUM(N3:N6) -> 40310
A9: Nota: valores de referência baseados no cenário REALISTA da projeção de 12 meses (ver 05-projecao-12-meses). Células em azul são estimativas/metas mensais e devem ser substituídas pelos números reais à medida que o negócio opera — Lucro líquido recalcula automaticamente.
