Workbook

Sheet Custos & Ponto Equilíbrio
A1: 🏠 CUSTOS FIXOS, VARIÁVEIS & PONTO DE EQUILÍBRIO | CASA RECHEADA
A3: ⚙️ PARÂMETROS DO NEGÓCIO
A4: CMV Meta Máximo — Alerta Vermelho % | B4: 0.35 | C4: % do preço de venda
A5: CMV Atenção — Alerta Amarelo % | B5: 0.3 | C5: faixa de atenção
A6: Markup Pães Recheados | B6: 2.9 | C6: 2.9 = preço é 2,9x o custo
A7: Markup Sobremesas Gourmet | B7: 3 | C7: 3.0 = preço é 3,0x o custo
A8: Fator de Desperdício Operacional % | B8: 0.08 | C8: perda de insumos / erro de produção
A9: Dias de produção / mês | B9: 20 | C9: dias
A10: Ticket médio por pedido R$ | B10: 28 | C10: ⚠️ VALIDAR EM CAMPO nas primeiras semanas
A11: Meta de lucro sobre o Ponto de Equilíbrio % | B11: 0.2 | C11: usado no faturamento-meta abaixo
A13: 🏠 CUSTOS FIXOS MENSAIS (sem aluguel — produção em residência)
A14: Item de Custo Fixo | B14: Mês 1 | C14: Mês 2 | D14: Mês 3 | E14: Mês 4 | F14: Mês 5 | G14: Mês 6 | H14: Total Sem. | I14: Média Mês
A15: Gás de cozinha (uso do negócio) | B15: 60 | C15: 65 | D15: 60 | E15: 55 | F15: 65 | G15: 70 | H15: =SUM(B15:G15) -> 375 | I15: =H15/6 -> 62.5
A16: Energia elétrica (parcela do negócio) | B16: 90 | C16: 95 | D16: 90 | E16: 85 | F16: 95 | G16: 100 | H16: =SUM(B16:G16) -> 555 | I16: =H16/6 -> 92.5
A17: Água (parcela do negócio) | B17: 30 | C17: 30 | D17: 28 | E17: 28 | F17: 32 | G17: 32 | H17: =SUM(B17:G17) -> 180 | I17: =H17/6 -> 30
A18: MEI — DAS mensal | B18: 76 | C18: 76 | D18: 76 | E18: 76 | F18: 76 | G18: 76 | H18: =SUM(B18:G18) -> 456 | I18: =H18/6 -> 76
A19: Internet / WhatsApp Business | B19: 50 | C19: 50 | D19: 50 | E19: 50 | F19: 50 | G19: 50 | H19: =SUM(B19:G19) -> 300 | I19: =H19/6 -> 50
A20: Manutenção de equipamentos | B20: 40 | C20: 20 | D20: 20 | E20: 40 | F20: 20 | G20: 20 | H20: =SUM(B20:G20) -> 160 | I20: =H20/6 -> 26.666667
A21: Marketing / Redes sociais (impulsionamento) | B21: 50 | C21: 50 | D21: 50 | E21: 50 | F21: 50 | G21: 50 | H21: =SUM(B21:G21) -> 300 | I21: =H21/6 -> 50
A22: TOTAL CUSTOS FIXOS | B22: =SUM(B15:B21) -> 396 | C22: =SUM(C15:C21) -> 386 | D22: =SUM(D15:D21) -> 374 | E22: =SUM(E15:E21) -> 384 | F22: =SUM(F15:F21) -> 388 | G22: =SUM(G15:G21) -> 398 | H22: =SUM(H15:H21) -> 2326 | I22: =SUM(I15:I21) -> 387.66667
A24: 📦 CUSTOS VARIÁVEIS MENSAIS
A25: Item Variável | B25: Mês 1 | C25: Mês 2 | D25: Mês 3 | E25: Mês 4 | F25: Mês 5 | G25: Mês 6 | H25: Total Sem. | I25: Média Mês
A26: CMV Insumos — Pães Recheados | B26: 420 | C26: 480 | D26: 560 | E26: 650 | F26: 700 | G26: 760 | H26: =SUM(B26:G26) -> 3570 | I26: =H26/6 -> 595
A27: CMV Insumos — Sobremesas Gourmet | B27: 380 | C27: 430 | D27: 500 | E27: 580 | F27: 630 | G27: 680 | H27: =SUM(B27:G27) -> 3200 | I27: =H27/6 -> 533.33333
A28: Embalagens e etiquetas | B28: 110 | C28: 130 | D28: 150 | E28: 170 | F28: 185 | G28: 200 | H28: =SUM(B28:G28) -> 945 | I28: =H28/6 -> 157.5
A29: Gás/insumos extras de produção | B29: 40 | C29: 45 | D29: 50 | E29: 55 | F29: 60 | G29: 65 | H29: =SUM(B29:G29) -> 315 | I29: =H29/6 -> 52.5
A30: Material de limpeza / descartáveis | B30: 35 | C30: 35 | D30: 40 | E30: 40 | F30: 45 | G30: 45 | H30: =SUM(B30:G30) -> 240 | I30: =H30/6 -> 40
A31: Outros variáveis | B31: 30 | C31: 30 | D31: 30 | E31: 30 | F31: 30 | G31: 30 | H31: =SUM(B31:G31) -> 180 | I31: =H31/6 -> 30
A32: TOTAL CUSTOS VARIÁVEIS | B32: =SUM(B26:B31) -> 1015 | C32: =SUM(C26:C31) -> 1150 | D32: =SUM(D26:D31) -> 1330 | E32: =SUM(E26:E31) -> 1525 | F32: =SUM(F26:F31) -> 1650 | G32: =SUM(G26:G31) -> 1780 | H32: =SUM(H26:H31) -> 8450 | I32: =SUM(I26:I31) -> 1408.3333
A34: 🎯 PONTO DE EQUILÍBRIO — CASA RECHEADA (cenário linear)
A35: Custo Fixo Médio Mensal R$ | B35: =I22 -> 387.66667
A36: Custo Variável Médio Mensal R$ | B36: =I32 -> 1408.3333
A37: Custo Total Mensal R$ | B37: =B35+B36 -> 1796
A38: Margem de Contribuição % (100% - CMV meta) | B38: =1-B4 -> 0.65
A39: PONTO DE EQUILÍBRIO MENSAL R$ | B39: =IFERROR(B37/B38,0) -> 2763.0769
A40: Ponto de Equilíbrio DIÁRIO R$ | B40: =IFERROR(B39/B9,0) -> 138.15385
A41: Pedidos/dia para atingir o PE (ticket médio) | B41: =IFERROR(CEILING(B40/B10,1),0) -> 5
A42: Faturamento Meta de Lucro R$/mês | B42: =B39*(1+B11) -> 3315.6923
A44: 📅 CENÁRIO COM SAZONALIDADE (datas comemorativas x período de vale)
A45: Fator Mês de Pico (Páscoa / Dia das Mães / Natal) | B45: 1.35 | C45: aumento de demanda em datas comemorativas
A46: Fator Mês de Vale (janeiro / férias escolares) | B46: 0.65 | C46: queda de demanda
A47: Reserva de Capital de Giro (meses) | B47: 3 | C47: padrão recomendado antes de abrir
A48: PE no Mês de Vale — Faturamento Necessário R$ | B48: =IFERROR(B39/B46,0) -> 4250.8876
A49: Caixa Mínimo p/ Sobreviver ao Vale (1 mês) R$ | B49: =B37 -> 1796
A50: RESERVA DE CAPITAL DE GIRO NECESSÁRIA R$ | B50: =B37*B47 -> 5388
A52: 💰 ORÇAMENTO DE ABERTURA (CAPEX) — investimento inicial
A53: Item de Investimento Inicial | B53: Estimativa Mínima R$ | C53: Estimativa Máxima R$ | D53: Obs
A54: Freezer horizontal 300L | B54: 1900 | C54: 2500
A55: Geladeira duplex (se não houver disponível em casa) | B55: 0 | C55: 2500 | D55: 0 se já possuir uma reservável
A56: Batedeira planetária 5L | B56: 650 | C56: 950
A57: Liquidificador profissional | B57: 350 | C57: 550
A58: Forno elétrico de bancada 45L | B58: 750 | C58: 1100
A59: Assadeiras + utensílios diversos | B59: 450 | C59: 700
A60: Balança digital de precisão | B60: 90 | C60: 150
A61: Seladora de embalagens | B61: 200 | C61: 320
A62: Bancada de produção em inox | B62: 700 | C62: 1100
A63: Embalagens + etiquetas (estoque inicial) | B63: 550 | C63: 750
A64: EPI + identidade visual / banner | B64: 250 | C64: 500
A65: Capital de Giro (reserva calculada acima) | B65: =B50 -> 5388 | C65: =B50 -> 5388 | D65: já calculado acima
A66: 💰 TOTAL INVESTIMENTO INICIAL NECESSÁRIO | B66: =SUM(B54:B65) -> 11278 | C66: =SUM(C54:C65) -> 16508 | D66: ⚠️ some este valor antes de comprometer qualquer real no projeto
A68: ✏️ Células AZUIS = editáveis | PRETO = fórmulas | CMV ≤ Atenção = 🟢 | entre Atenção e Meta = 🟡 | acima da Meta = 🔴

Sheet Fichas Técnicas - Pães
A1: 🥖 FICHAS TÉCNICAS — PÃES RECHEADOS ARTESANAIS | CASA RECHEADA
A3: ⚙️ PARÂMETROS (referenciam a aba Custos & Ponto Equilíbrio)
A4: Markup Pães | B4: ='Custos & Ponto Equilíbrio'!B6 -> 2.9 | C4: Desperdício Operacional | D4: ='Custos & Ponto Equilíbrio'!B8 -> 0.08 | E4: CMV Meta | F4: ='Custos & Ponto Equilíbrio'!B4 -> 0.35 | G4: 💡 AZUL = editável | PRETO = fórmula
A6: 🥖 PÃO RECHEADO FRANGO + QUEIJO [P001] — bastonete italiano ~90g, rende 20 unidades
A7: Ingrediente | B7: Unid. | C7: Qtd. Receita (lote) | D7: Preço Compra R$ | E7: Custo Bruto R$ | F7: F. Correção | G7: Custo Líquido R$ | H7: % no Produto | I7: Obs / Fornecedor | J7: Atualizado em
A8: Farinha de trigo | B8: g | C8: 1000 | D8: 0.0055 | E8: =C8*D8 -> 5.5 | F8: 1 | G8: =E8*F8 -> 5.5 | H8: =IFERROR(G8/SUM(G8:G19),0) -> 0.11221055 | I8: Atacarejo local | J8: =TODAY() -> 46241
A9: Fermento biológico seco | B9: g | C9: 10 | D9: 0.036 | E9: =C9*D9 -> 0.36 | F9: 1 | G9: =E9*F9 -> 0.36 | H9: =IFERROR(G9/SUM(G8:G19),0) -> 0.0073446904 | J9: =TODAY() -> 46241
A10: Açúcar | B10: g | C10: 80 | D10: 0.0045 | E10: =C10*D10 -> 0.36 | F10: 1 | G10: =E10*F10 -> 0.36 | H10: =IFERROR(G10/SUM(G8:G19),0) -> 0.0073446904 | J10: =TODAY() -> 46241
A11: Sal | B11: g | C11: 15 | D11: 0.003 | E11: =C11*D11 -> 0.045 | F11: 1 | G11: =E11*F11 -> 0.045 | H11: =IFERROR(G11/SUM(G8:G19),0) -> 0.0009180863 | J11: =TODAY() -> 46241
A12: Ovos | B12: un | C12: 2 | D12: 1 | E12: =C12*D12 -> 2 | F12: 1 | G12: =E12*F12 -> 2 | H12: =IFERROR(G12/SUM(G8:G19),0) -> 0.040803836 | J12: =TODAY() -> 46241
A13: Leite | B13: ml | C13: 300 | D13: 0.005 | E13: =C13*D13 -> 1.5 | F13: 1 | G13: =E13*F13 -> 1.5 | H13: =IFERROR(G13/SUM(G8:G19),0) -> 0.030602877 | J13: =TODAY() -> 46241
A14: Manteiga | B14: g | C14: 60 | D14: 0.035 | E14: =C14*D14 -> 2.1 | F14: 1 | G14: =E14*F14 -> 2.1 | H14: =IFERROR(G14/SUM(G8:G19),0) -> 0.042844027 | J14: =TODAY() -> 46241
A15: Frango (peito) cozido e desfiado | B15: g | C15: 500 | D15: 0.022 | E15: =C15*D15 -> 11 | F15: 1.05 | G15: =E15*F15 -> 11.55 | H15: =IFERROR(G15/SUM(G8:G19),0) -> 0.23564215 | I15: perda de apara/gordura | J15: =TODAY() -> 46241
A16: Queijo muçarela ralado | B16: g | C16: 300 | D16: 0.032 | E16: =C16*D16 -> 9.6 | F16: 1 | G16: =E16*F16 -> 9.6 | H16: =IFERROR(G16/SUM(G8:G19),0) -> 0.19585841 | J16: =TODAY() -> 46241
A17: Requeijão | B17: g | C17: 100 | D17: 0.07 | E17: =C17*D17 -> 7 | F17: 1 | G17: =E17*F17 -> 7 | H17: =IFERROR(G17/SUM(G8:G19),0) -> 0.14281342 | J17: =TODAY() -> 46241
A18: Temperos (cebola, alho, sal, cheiro-verde) | B18: vb | C18: 1 | D18: 1 | E18: =C18*D18 -> 1 | F18: 1 | G18: =E18*F18 -> 1 | H18: =IFERROR(G18/SUM(G8:G19),0) -> 0.020401918 | I18: verba estimada | J18: =TODAY() -> 46241
A19: Embalagem (saco kraft + etiqueta) | B19: un | C19: 20 | D19: 0.4 | E19: =C19*D19 -> 8 | F19: 1 | G19: =E19*F19 -> 8 | H19: =IFERROR(G19/SUM(G8:G19),0) -> 0.16321534 | I19: p/ lote de 20un | J19: =TODAY() -> 46241
A20: 💵 CUSTO TOTAL DO LOTE — SEM PERDA (R$) | G20: =SUM(G8:G19) -> 49.015
A21: ⚠️ CUSTO REAL c/ DESPERDÍCIO OPERACIONAL | G21: =G20*(1+'Custos & Ponto Equilíbrio'!$B$8) -> 52.9362
A22: 📦 RENDIMENTO DA RECEITA (unidades) | G22: 20
A23: 🔹 CUSTO UNITÁRIO (R$/un) | G23: =G21/G22 -> 2.64681
A24: 🏷️ PREÇO DE VENDA SUGERIDO (R$/un) — Markup | G24: =G23*'Custos & Ponto Equilíbrio'!$B$6 -> 7.675749
A25: 📊 CMV % real (meta e alerta na aba Custos) | G25: =IFERROR(G23/G24,0) -> 0.34482759
A26: 📈 MARGEM DE LUCRO (%) | G26: =IFERROR(1-G25,0) -> 0.65517241
A28: 🥖 PÃO RECHEADO CALABRESA + QUEIJO [P002] — bastonete italiano ~90g, rende 20 unidades
A29: Ingrediente | B29: Unid. | C29: Qtd. Receita (lote) | D29: Preço Compra R$ | E29: Custo Bruto R$ | F29: F. Correção | G29: Custo Líquido R$ | H29: % no Produto | I29: Obs / Fornecedor | J29: Atualizado em
A30: Farinha de trigo | B30: g | C30: 1000 | D30: 0.0055 | E30: =C30*D30 -> 5.5 | F30: 1 | G30: =E30*F30 -> 5.5 | H30: =IFERROR(G30/SUM(G30:G40),0) -> 0.14602416 | I30: Atacarejo local | J30: =TODAY() -> 46241
A31: Fermento biológico seco | B31: g | C31: 10 | D31: 0.036 | E31: =C31*D31 -> 0.36 | F31: 1 | G31: =E31*F31 -> 0.36 | H31: =IFERROR(G31/SUM(G30:G40),0) -> 0.009557945 | J31: =TODAY() -> 46241
A32: Açúcar | B32: g | C32: 80 | D32: 0.0045 | E32: =C32*D32 -> 0.36 | F32: 1 | G32: =E32*F32 -> 0.36 | H32: =IFERROR(G32/SUM(G30:G40),0) -> 0.009557945 | J32: =TODAY() -> 46241
A33: Sal | B33: g | C33: 15 | D33: 0.003 | E33: =C33*D33 -> 0.045 | F33: 1 | G33: =E33*F33 -> 0.045 | H33: =IFERROR(G33/SUM(G30:G40),0) -> 0.0011947431 | J33: =TODAY() -> 46241
A34: Ovos | B34: un | C34: 2 | D34: 1 | E34: =C34*D34 -> 2 | F34: 1 | G34: =E34*F34 -> 2 | H34: =IFERROR(G34/SUM(G30:G40),0) -> 0.053099695 | J34: =TODAY() -> 46241
A35: Leite | B35: ml | C35: 300 | D35: 0.005 | E35: =C35*D35 -> 1.5 | F35: 1 | G35: =E35*F35 -> 1.5 | H35: =IFERROR(G35/SUM(G30:G40),0) -> 0.039824771 | J35: =TODAY() -> 46241
A36: Manteiga | B36: g | C36: 60 | D36: 0.035 | E36: =C36*D36 -> 2.1 | F36: 1 | G36: =E36*F36 -> 2.1 | H36: =IFERROR(G36/SUM(G30:G40),0) -> 0.055754679 | J36: =TODAY() -> 46241
A37: Calabresa moída/fatiada | B37: g | C37: 400 | D37: 0.022 | E37: =C37*D37 -> 8.8 | F37: 1 | G37: =E37*F37 -> 8.8 | H37: =IFERROR(G37/SUM(G30:G40),0) -> 0.23363866 | I37: Mercado local | J37: =TODAY() -> 46241
A38: Queijo muçarela ralado | B38: g | C38: 250 | D38: 0.032 | E38: =C38*D38 -> 8 | F38: 1 | G38: =E38*F38 -> 8 | H38: =IFERROR(G38/SUM(G30:G40),0) -> 0.21239878 | J38: =TODAY() -> 46241
A39: Cebola / temperos | B39: vb | C39: 1 | D39: 1 | E39: =C39*D39 -> 1 | F39: 1 | G39: =E39*F39 -> 1 | H39: =IFERROR(G39/SUM(G30:G40),0) -> 0.026549847 | I39: verba estimada | J39: =TODAY() -> 46241
A40: Embalagem (saco kraft + etiqueta) | B40: un | C40: 20 | D40: 0.4 | E40: =C40*D40 -> 8 | F40: 1 | G40: =E40*F40 -> 8 | H40: =IFERROR(G40/SUM(G30:G40),0) -> 0.21239878 | I40: p/ lote de 20un | J40: =TODAY() -> 46241
A41: 💵 CUSTO TOTAL DO LOTE — SEM PERDA (R$) | G41: =SUM(G30:G40) -> 37.665
A42: ⚠️ CUSTO REAL c/ DESPERDÍCIO OPERACIONAL | G42: =G41*(1+'Custos & Ponto Equilíbrio'!$B$8) -> 40.6782
A43: 📦 RENDIMENTO DA RECEITA (unidades) | G43: 20
A44: 🔹 CUSTO UNITÁRIO (R$/un) | G44: =G42/G43 -> 2.03391
A45: 🏷️ PREÇO DE VENDA SUGERIDO (R$/un) — Markup | G45: =G44*'Custos & Ponto Equilíbrio'!$B$6 -> 5.898339
A46: 📊 CMV % real (meta e alerta na aba Custos) | G46: =IFERROR(G44/G45,0) -> 0.34482759
A47: 📈 MARGEM DE LUCRO (%) | G47: =IFERROR(1-G46,0) -> 0.65517241
A49: 🥖 PÃO RECHEADO PRESUNTO + QUEIJO [P003] — bastonete italiano ~90g, rende 20 unidades
A50: Ingrediente | B50: Unid. | C50: Qtd. Receita (lote) | D50: Preço Compra R$ | E50: Custo Bruto R$ | F50: F. Correção | G50: Custo Líquido R$ | H50: % no Produto | I50: Obs / Fornecedor | J50: Atualizado em
A51: Farinha de trigo | B51: g | C51: 1000 | D51: 0.0055 | E51: =C51*D51 -> 5.5 | F51: 1 | G51: =E51*F51 -> 5.5 | H51: =IFERROR(G51/SUM(G51:G60),0) -> 0.14525287 | I51: Atacarejo local | J51: =TODAY() -> 46241
A52: Fermento biológico seco | B52: g | C52: 10 | D52: 0.036 | E52: =C52*D52 -> 0.36 | F52: 1 | G52: =E52*F52 -> 0.36 | H52: =IFERROR(G52/SUM(G51:G60),0) -> 0.0095074607 | J52: =TODAY() -> 46241
A53: Açúcar | B53: g | C53: 80 | D53: 0.0045 | E53: =C53*D53 -> 0.36 | F53: 1 | G53: =E53*F53 -> 0.36 | H53: =IFERROR(G53/SUM(G51:G60),0) -> 0.0095074607 | J53: =TODAY() -> 46241
A54: Sal | B54: g | C54: 15 | D54: 0.003 | E54: =C54*D54 -> 0.045 | F54: 1 | G54: =E54*F54 -> 0.045 | H54: =IFERROR(G54/SUM(G51:G60),0) -> 0.0011884326 | J54: =TODAY() -> 46241
A55: Ovos | B55: un | C55: 2 | D55: 1 | E55: =C55*D55 -> 2 | F55: 1 | G55: =E55*F55 -> 2 | H55: =IFERROR(G55/SUM(G51:G60),0) -> 0.052819226 | J55: =TODAY() -> 46241
A56: Leite | B56: ml | C56: 300 | D56: 0.005 | E56: =C56*D56 -> 1.5 | F56: 1 | G56: =E56*F56 -> 1.5 | H56: =IFERROR(G56/SUM(G51:G60),0) -> 0.03961442 | J56: =TODAY() -> 46241
A57: Manteiga | B57: g | C57: 60 | D57: 0.035 | E57: =C57*D57 -> 2.1 | F57: 1 | G57: =E57*F57 -> 2.1 | H57: =IFERROR(G57/SUM(G51:G60),0) -> 0.055460188 | J57: =TODAY() -> 46241
A58: Presunto fatiado | B58: g | C58: 300 | D58: 0.028 | E58: =C58*D58 -> 8.4 | F58: 1 | G58: =E58*F58 -> 8.4 | H58: =IFERROR(G58/SUM(G51:G60),0) -> 0.22184075 | J58: =TODAY() -> 46241
A59: Queijo muçarela ralado | B59: g | C59: 300 | D59: 0.032 | E59: =C59*D59 -> 9.6 | F59: 1 | G59: =E59*F59 -> 9.6 | H59: =IFERROR(G59/SUM(G51:G60),0) -> 0.25353229 | J59: =TODAY() -> 46241
A60: Embalagem (saco kraft + etiqueta) | B60: un | C60: 20 | D60: 0.4 | E60: =C60*D60 -> 8 | F60: 1 | G60: =E60*F60 -> 8 | H60: =IFERROR(G60/SUM(G51:G60),0) -> 0.2112769 | I60: p/ lote de 20un | J60: =TODAY() -> 46241
A61: 💵 CUSTO TOTAL DO LOTE — SEM PERDA (R$) | G61: =SUM(G51:G60) -> 37.865
A62: ⚠️ CUSTO REAL c/ DESPERDÍCIO OPERACIONAL | G62: =G61*(1+'Custos & Ponto Equilíbrio'!$B$8) -> 40.8942
A63: 📦 RENDIMENTO DA RECEITA (unidades) | G63: 20
A64: 🔹 CUSTO UNITÁRIO (R$/un) | G64: =G62/G63 -> 2.04471
A65: 🏷️ PREÇO DE VENDA SUGERIDO (R$/un) — Markup | G65: =G64*'Custos & Ponto Equilíbrio'!$B$6 -> 5.929659
A66: 📊 CMV % real (meta e alerta na aba Custos) | G66: =IFERROR(G64/G65,0) -> 0.34482759
A67: 📈 MARGEM DE LUCRO (%) | G67: =IFERROR(1-G66,0) -> 0.65517241
A69: 🥖 PÃO RECHEADO RÚCULA + QUEIJO [P004] — bastonete italiano ~90g, rende 20 unidades
A70: Ingrediente | B70: Unid. | C70: Qtd. Receita (lote) | D70: Preço Compra R$ | E70: Custo Bruto R$ | F70: F. Correção | G70: Custo Líquido R$ | H70: % no Produto | I70: Obs / Fornecedor | J70: Atualizado em
A71: Farinha de trigo | B71: g | C71: 1000 | D71: 0.0055 | E71: =C71*D71 -> 5.5 | F71: 1 | G71: =E71*F71 -> 5.5 | H71: =IFERROR(G71/SUM(G71:G81),0) -> 0.12313892 | I71: Atacarejo local | J71: =TODAY() -> 46241
A72: Fermento biológico seco | B72: g | C72: 10 | D72: 0.036 | E72: =C72*D72 -> 0.36 | F72: 1 | G72: =E72*F72 -> 0.36 | H72: =IFERROR(G72/SUM(G71:G81),0) -> 0.0080600022 | J72: =TODAY() -> 46241
A73: Açúcar | B73: g | C73: 80 | D73: 0.0045 | E73: =C73*D73 -> 0.36 | F73: 1 | G73: =E73*F73 -> 0.36 | H73: =IFERROR(G73/SUM(G71:G81),0) -> 0.0080600022 | J73: =TODAY() -> 46241
A74: Sal | B74: g | C74: 15 | D74: 0.003 | E74: =C74*D74 -> 0.045 | F74: 1 | G74: =E74*F74 -> 0.045 | H74: =IFERROR(G74/SUM(G71:G81),0) -> 0.0010075003 | J74: =TODAY() -> 46241
A75: Ovos | B75: un | C75: 2 | D75: 1 | E75: =C75*D75 -> 2 | F75: 1 | G75: =E75*F75 -> 2 | H75: =IFERROR(G75/SUM(G71:G81),0) -> 0.04477779 | J75: =TODAY() -> 46241
A76: Leite | B76: ml | C76: 300 | D76: 0.005 | E76: =C76*D76 -> 1.5 | F76: 1 | G76: =E76*F76 -> 1.5 | H76: =IFERROR(G76/SUM(G71:G81),0) -> 0.033583343 | J76: =TODAY() -> 46241
A77: Manteiga | B77: g | C77: 60 | D77: 0.035 | E77: =C77*D77 -> 2.1 | F77: 1 | G77: =E77*F77 -> 2.1 | H77: =IFERROR(G77/SUM(G71:G81),0) -> 0.04701668 | J77: =TODAY() -> 46241
A78: Rúcula fresca | B78: un (maço) | C78: 2 | D78: 4 | E78: =C78*D78 -> 8 | F78: 1.15 | G78: =E78*F78 -> 9.2 | H78: =IFERROR(G78/SUM(G71:G81),0) -> 0.20597783 | I78: perda de folhas | J78: =TODAY() -> 46241
A79: Queijo/ricota | B79: g | C79: 300 | D79: 0.032 | E79: =C79*D79 -> 9.6 | F79: 1 | G79: =E79*F79 -> 9.6 | H79: =IFERROR(G79/SUM(G71:G81),0) -> 0.21493339 | J79: =TODAY() -> 46241
A80: Tomate seco | B80: g | C80: 100 | D80: 0.06 | E80: =C80*D80 -> 6 | F80: 1 | G80: =E80*F80 -> 6 | H80: =IFERROR(G80/SUM(G71:G81),0) -> 0.13433337 | J80: =TODAY() -> 46241
A81: Embalagem (saco kraft + etiqueta) | B81: un | C81: 20 | D81: 0.4 | E81: =C81*D81 -> 8 | F81: 1 | G81: =E81*F81 -> 8 | H81: =IFERROR(G81/SUM(G71:G81),0) -> 0.17911116 | I81: p/ lote de 20un | J81: =TODAY() -> 46241
A82: 💵 CUSTO TOTAL DO LOTE — SEM PERDA (R$) | G82: =SUM(G71:G81) -> 44.665
A83: ⚠️ CUSTO REAL c/ DESPERDÍCIO OPERACIONAL | G83: =G82*(1+'Custos & Ponto Equilíbrio'!$B$8) -> 48.2382
A84: 📦 RENDIMENTO DA RECEITA (unidades) | G84: 20
A85: 🔹 CUSTO UNITÁRIO (R$/un) | G85: =G83/G84 -> 2.41191
A86: 🏷️ PREÇO DE VENDA SUGERIDO (R$/un) — Markup | G86: =G85*'Custos & Ponto Equilíbrio'!$B$6 -> 6.994539
A87: 📊 CMV % real (meta e alerta na aba Custos) | G87: =IFERROR(G85/G86,0) -> 0.34482759
A88: 📈 MARGEM DE LUCRO (%) | G88: =IFERROR(1-G87,0) -> 0.65517241

Sheet Fichas Técnicas - Sobremesas
A1: 🍰 FICHAS TÉCNICAS — SOBREMESAS GOURMET NO POTE | CASA RECHEADA
A3: ⚙️ PARÂMETROS (referenciam a aba Custos & Ponto Equilíbrio)
A4: Markup Sobremesas | B4: ='Custos & Ponto Equilíbrio'!B7 -> 3 | C4: Desperdício Operacional | D4: ='Custos & Ponto Equilíbrio'!B8 -> 0.08 | E4: CMV Meta | F4: ='Custos & Ponto Equilíbrio'!B4 -> 0.35 | G4: 💡 AZUL = editável | PRETO = fórmula
A6: 🍫 MOUSSE DE CHOCOLATE [S001] — pote 200ml, rende 10 unidades
A7: Ingrediente | B7: Unid. | C7: Qtd. Receita (lote) | D7: Preço Compra R$ | E7: Custo Bruto R$ | F7: F. Correção | G7: Custo Líquido R$ | H7: % no Produto | I7: Obs / Fornecedor | J7: Atualizado em
A8: Chocolate meio amargo | B8: g | C8: 300 | D8: 0.04 | E8: =C8*D8 -> 12 | F8: 1 | G8: =E8*F8 -> 12 | H8: =IFERROR(G8/SUM(G8:G12),0) -> 0.38461538 | J8: =TODAY() -> 46241
A9: Creme de leite | B9: un (cx 200g) | C9: 2 | D9: 4 | E9: =C9*D9 -> 8 | F9: 1 | G9: =E9*F9 -> 8 | H9: =IFERROR(G9/SUM(G8:G12),0) -> 0.25641026 | J9: =TODAY() -> 46241
A10: Leite condensado | B10: un (lata) | C10: 1 | D10: 7 | E10: =C10*D10 -> 7 | F10: 1 | G10: =E10*F10 -> 7 | H10: =IFERROR(G10/SUM(G8:G12),0) -> 0.22435897 | J10: =TODAY() -> 46241
A11: Claras de ovo | B11: un | C11: 3 | D11: 1 | E11: =C11*D11 -> 3 | F11: 1 | G11: =E11*F11 -> 3 | H11: =IFERROR(G11/SUM(G8:G12),0) -> 0.096153846 | J11: =TODAY() -> 46241
A12: Embalagem (pote 200ml + tampa + etiqueta) | B12: un | C12: 10 | D12: 0.12 | E12: =C12*D12 -> 1.2 | F12: 1 | G12: =E12*F12 -> 1.2 | H12: =IFERROR(G12/SUM(G8:G12),0) -> 0.038461538 | I12: p/ lote de 10un | J12: =TODAY() -> 46241
A13: 💵 CUSTO TOTAL DO LOTE — SEM PERDA (R$) | G13: =SUM(G8:G12) -> 31.2
A14: ⚠️ CUSTO REAL c/ DESPERDÍCIO OPERACIONAL | G14: =G13*(1+'Custos & Ponto Equilíbrio'!$B$8) -> 33.696
A15: 📦 RENDIMENTO DA RECEITA (unidades) | G15: 10
A16: 🔹 CUSTO UNITÁRIO (R$/un) | G16: =G14/G15 -> 3.3696
A17: 🏷️ PREÇO DE VENDA SUGERIDO (R$/un) — Markup | G17: =G16*'Custos & Ponto Equilíbrio'!$B$7 -> 10.1088
A18: 📊 CMV % real (meta e alerta na aba Custos) | G18: =IFERROR(G16/G17,0) -> 0.33333333
A19: 📈 MARGEM DE LUCRO (%) | G19: =IFERROR(1-G18,0) -> 0.66666667
A21: 🥭 MOUSSE DE MARACUJÁ [S002] — pote 200ml, rende 10 unidades
A22: Ingrediente | B22: Unid. | C22: Qtd. Receita (lote) | D22: Preço Compra R$ | E22: Custo Bruto R$ | F22: F. Correção | G22: Custo Líquido R$ | H22: % no Produto | I22: Obs / Fornecedor | J22: Atualizado em
A23: Suco concentrado de maracujá | B23: ml | C23: 200 | D23: 0.03 | E23: =C23*D23 -> 6 | F23: 1 | G23: =E23*F23 -> 6 | H23: =IFERROR(G23/SUM(G23:G27),0) -> 0.24793388 | J23: =TODAY() -> 46241
A24: Leite condensado | B24: un (lata) | C24: 1 | D24: 7 | E24: =C24*D24 -> 7 | F24: 1 | G24: =E24*F24 -> 7 | H24: =IFERROR(G24/SUM(G23:G27),0) -> 0.2892562 | J24: =TODAY() -> 46241
A25: Creme de leite | B25: un (cx 200g) | C25: 2 | D25: 4 | E25: =C25*D25 -> 8 | F25: 1 | G25: =E25*F25 -> 8 | H25: =IFERROR(G25/SUM(G23:G27),0) -> 0.33057851 | J25: =TODAY() -> 46241
A26: Gelatina incolor sem sabor | B26: un (envelope) | C26: 1 | D26: 2 | E26: =C26*D26 -> 2 | F26: 1 | G26: =E26*F26 -> 2 | H26: =IFERROR(G26/SUM(G23:G27),0) -> 0.082644628 | J26: =TODAY() -> 46241
A27: Embalagem (pote 200ml + tampa + etiqueta) | B27: un | C27: 10 | D27: 0.12 | E27: =C27*D27 -> 1.2 | F27: 1 | G27: =E27*F27 -> 1.2 | H27: =IFERROR(G27/SUM(G23:G27),0) -> 0.049586777 | I27: p/ lote de 10un | J27: =TODAY() -> 46241
A28: 💵 CUSTO TOTAL DO LOTE — SEM PERDA (R$) | G28: =SUM(G23:G27) -> 24.2
A29: ⚠️ CUSTO REAL c/ DESPERDÍCIO OPERACIONAL | G29: =G28*(1+'Custos & Ponto Equilíbrio'!$B$8) -> 26.136
A30: 📦 RENDIMENTO DA RECEITA (unidades) | G30: 10
A31: 🔹 CUSTO UNITÁRIO (R$/un) | G31: =G29/G30 -> 2.6136
A32: 🏷️ PREÇO DE VENDA SUGERIDO (R$/un) — Markup | G32: =G31*'Custos & Ponto Equilíbrio'!$B$7 -> 7.8408
A33: 📊 CMV % real (meta e alerta na aba Custos) | G33: =IFERROR(G31/G32,0) -> 0.33333333
A34: 📈 MARGEM DE LUCRO (%) | G34: =IFERROR(1-G33,0) -> 0.66666667
A36: 🍋 MOUSSE DE LIMÃO [S003] — pote 200ml, rende 10 unidades
A37: Ingrediente | B37: Unid. | C37: Qtd. Receita (lote) | D37: Preço Compra R$ | E37: Custo Bruto R$ | F37: F. Correção | G37: Custo Líquido R$ | H37: % no Produto | I37: Obs / Fornecedor | J37: Atualizado em
A38: Suco e raspas de limão | B38: ml | C38: 150 | D38: 0.02 | E38: =C38*D38 -> 3 | F38: 1.15 | G38: =E38*F38 -> 3.45 | H38: =IFERROR(G38/SUM(G38:G42),0) -> 0.15935335 | I38: perda de casca/raspas | J38: =TODAY() -> 46241
A39: Leite condensado | B39: un (lata) | C39: 1 | D39: 7 | E39: =C39*D39 -> 7 | F39: 1 | G39: =E39*F39 -> 7 | H39: =IFERROR(G39/SUM(G38:G42),0) -> 0.32332564 | J39: =TODAY() -> 46241
A40: Creme de leite | B40: un (cx 200g) | C40: 2 | D40: 4 | E40: =C40*D40 -> 8 | F40: 1 | G40: =E40*F40 -> 8 | H40: =IFERROR(G40/SUM(G38:G42),0) -> 0.36951501 | J40: =TODAY() -> 46241
A41: Gelatina incolor sem sabor | B41: un (envelope) | C41: 1 | D41: 2 | E41: =C41*D41 -> 2 | F41: 1 | G41: =E41*F41 -> 2 | H41: =IFERROR(G41/SUM(G38:G42),0) -> 0.092378753 | J41: =TODAY() -> 46241
A42: Embalagem (pote 200ml + tampa + etiqueta) | B42: un | C42: 10 | D42: 0.12 | E42: =C42*D42 -> 1.2 | F42: 1 | G42: =E42*F42 -> 1.2 | H42: =IFERROR(G42/SUM(G38:G42),0) -> 0.055427252 | I42: p/ lote de 10un | J42: =TODAY() -> 46241
A43: 💵 CUSTO TOTAL DO LOTE — SEM PERDA (R$) | G43: =SUM(G38:G42) -> 21.65
A44: ⚠️ CUSTO REAL c/ DESPERDÍCIO OPERACIONAL | G44: =G43*(1+'Custos & Ponto Equilíbrio'!$B$8) -> 23.382
A45: 📦 RENDIMENTO DA RECEITA (unidades) | G45: 10
A46: 🔹 CUSTO UNITÁRIO (R$/un) | G46: =G44/G45 -> 2.3382
A47: 🏷️ PREÇO DE VENDA SUGERIDO (R$/un) — Markup | G47: =G46*'Custos & Ponto Equilíbrio'!$B$7 -> 7.0146
A48: 📊 CMV % real (meta e alerta na aba Custos) | G48: =IFERROR(G46/G47,0) -> 0.33333333
A49: 📈 MARGEM DE LUCRO (%) | G49: =IFERROR(1-G48,0) -> 0.66666667
A51: 🍌 BANOFFEE NO POTE [S004] — pote 200ml, rende 8 unidades
A52: Ingrediente | B52: Unid. | C52: Qtd. Receita (lote) | D52: Preço Compra R$ | E52: Custo Bruto R$ | F52: F. Correção | G52: Custo Líquido R$ | H52: % no Produto | I52: Obs / Fornecedor | J52: Atualizado em
A53: Bolacha triturada (base) | B53: g | C53: 200 | D53: 0.02 | E53: =C53*D53 -> 4 | F53: 1 | G53: =E53*F53 -> 4 | H53: =IFERROR(G53/SUM(G53:G59),0) -> 0.13582343 | J53: =TODAY() -> 46241
A54: Manteiga | B54: g | C54: 50 | D54: 0.035 | E54: =C54*D54 -> 1.75 | F54: 1 | G54: =E54*F54 -> 1.75 | H54: =IFERROR(G54/SUM(G53:G59),0) -> 0.05942275 | J54: =TODAY() -> 46241
A55: Doce de leite | B55: g | C55: 400 | D55: 0.0225 | E55: =C55*D55 -> 9 | F55: 1 | G55: =E55*F55 -> 9 | H55: =IFERROR(G55/SUM(G53:G59),0) -> 0.30560272 | J55: =TODAY() -> 46241
A56: Banana | B56: un | C56: 4 | D56: 1 | E56: =C56*D56 -> 4 | F56: 1.05 | G56: =E56*F56 -> 4.2 | H56: =IFERROR(G56/SUM(G53:G59),0) -> 0.1426146 | I56: perda de casca/pontas | J56: =TODAY() -> 46241
A57: Chantilly | B57: g | C57: 200 | D57: 0.03 | E57: =C57*D57 -> 6 | F57: 1 | G57: =E57*F57 -> 6 | H57: =IFERROR(G57/SUM(G53:G59),0) -> 0.20373514 | J57: =TODAY() -> 46241
A58: Chocolate em raspas (finalização) | B58: g | C58: 50 | D58: 0.06 | E58: =C58*D58 -> 3 | F58: 1 | G58: =E58*F58 -> 3 | H58: =IFERROR(G58/SUM(G53:G59),0) -> 0.10186757 | J58: =TODAY() -> 46241
A59: Embalagem (pote 200ml + tampa + etiqueta) | B59: un | C59: 8 | D59: 0.1875 | E59: =C59*D59 -> 1.5 | F59: 1 | G59: =E59*F59 -> 1.5 | H59: =IFERROR(G59/SUM(G53:G59),0) -> 0.050933786 | I59: p/ lote de 8un | J59: =TODAY() -> 46241
A60: 💵 CUSTO TOTAL DO LOTE — SEM PERDA (R$) | G60: =SUM(G53:G59) -> 29.45
A61: ⚠️ CUSTO REAL c/ DESPERDÍCIO OPERACIONAL | G61: =G60*(1+'Custos & Ponto Equilíbrio'!$B$8) -> 31.806
A62: 📦 RENDIMENTO DA RECEITA (unidades) | G62: 8
A63: 🔹 CUSTO UNITÁRIO (R$/un) | G63: =G61/G62 -> 3.97575
A64: 🏷️ PREÇO DE VENDA SUGERIDO (R$/un) — Markup | G64: =G63*'Custos & Ponto Equilíbrio'!$B$7 -> 11.92725
A65: 📊 CMV % real (meta e alerta na aba Custos) | G65: =IFERROR(G63/G64,0) -> 0.33333333
A66: 📈 MARGEM DE LUCRO (%) | G66: =IFERROR(1-G65,0) -> 0.66666667
A68: 🍮 PAVÊ NO POTE [S005] — pote 200ml, rende 10 unidades
A69: Ingrediente | B69: Unid. | C69: Qtd. Receita (lote) | D69: Preço Compra R$ | E69: Custo Bruto R$ | F69: F. Correção | G69: Custo Líquido R$ | H69: % no Produto | I69: Obs / Fornecedor | J69: Atualizado em
A70: Biscoito champanhe/maisena | B70: g | C70: 200 | D70: 0.025 | E70: =C70*D70 -> 5 | F70: 1 | G70: =E70*F70 -> 5 | H70: =IFERROR(G70/SUM(G70:G75),0) -> 0.1984127 | J70: =TODAY() -> 46241
A71: Leite condensado | B71: un (lata) | C71: 1 | D71: 7 | E71: =C71*D71 -> 7 | F71: 1 | G71: =E71*F71 -> 7 | H71: =IFERROR(G71/SUM(G70:G75),0) -> 0.27777778 | J71: =TODAY() -> 46241
A72: Leite | B72: ml | C72: 500 | D72: 0.005 | E72: =C72*D72 -> 2.5 | F72: 1 | G72: =E72*F72 -> 2.5 | H72: =IFERROR(G72/SUM(G70:G75),0) -> 0.099206349 | J72: =TODAY() -> 46241
A73: Creme de leite | B73: un (cx 200g) | C73: 2 | D73: 4 | E73: =C73*D73 -> 8 | F73: 1 | G73: =E73*F73 -> 8 | H73: =IFERROR(G73/SUM(G70:G75),0) -> 0.31746032 | J73: =TODAY() -> 46241
A74: Chocolate em pó (finalização) | B74: g | C74: 50 | D74: 0.03 | E74: =C74*D74 -> 1.5 | F74: 1 | G74: =E74*F74 -> 1.5 | H74: =IFERROR(G74/SUM(G70:G75),0) -> 0.05952381 | J74: =TODAY() -> 46241
A75: Embalagem (pote 200ml + tampa + etiqueta) | B75: un | C75: 10 | D75: 0.12 | E75: =C75*D75 -> 1.2 | F75: 1 | G75: =E75*F75 -> 1.2 | H75: =IFERROR(G75/SUM(G70:G75),0) -> 0.047619048 | I75: p/ lote de 10un | J75: =TODAY() -> 46241
A76: 💵 CUSTO TOTAL DO LOTE — SEM PERDA (R$) | G76: =SUM(G70:G75) -> 25.2
A77: ⚠️ CUSTO REAL c/ DESPERDÍCIO OPERACIONAL | G77: =G76*(1+'Custos & Ponto Equilíbrio'!$B$8) -> 27.216
A78: 📦 RENDIMENTO DA RECEITA (unidades) | G78: 10
A79: 🔹 CUSTO UNITÁRIO (R$/un) | G79: =G77/G78 -> 2.7216
A80: 🏷️ PREÇO DE VENDA SUGERIDO (R$/un) — Markup | G80: =G79*'Custos & Ponto Equilíbrio'!$B$7 -> 8.1648
A81: 📊 CMV % real (meta e alerta na aba Custos) | G81: =IFERROR(G79/G80,0) -> 0.33333333
A82: 📈 MARGEM DE LUCRO (%) | G82: =IFERROR(1-G81,0) -> 0.66666667

Sheet Cardápio & Preços
A1: 📋 CASA RECHEADA — CARDÁPIO MESTRE & CONTROLE DE CMV
A3: TODOS OS ITENS DO CARDÁPIO — VINCULADOS ÀS FICHAS TÉCNICAS
A4: # | B4: Produto / Item | C4: Categoria | D4: Custo Unit. R$ | E4: Preço Venda R$ | F4: CMV % | G4: Markup | H4: Status
A5: ▶ PÃES RECHEADOS
A6: P001 | B6: 🥖 PÃO RECHEADO FRANGO + QUEIJO | C6: PÃO | D6: ='Fichas Técnicas - Pães'!G23 -> 2.64681 | E6: ='Fichas Técnicas - Pães'!G24 -> 7.675749 | F6: ='Fichas Técnicas - Pães'!G25 -> 0.34482759 | G6: =IFERROR(E6/D6,0) -> 2.9 | H6: =IF(F6<='Custos & Ponto Equilíbrio'!$B$5,"🟢 Ideal",IF(F6<='Custos & Ponto Equilíbrio'!$B$4,"🟡 Atenção","🔴 Alto")) -> 🟡 Atenção
A7: P002 | B7: 🥖 PÃO RECHEADO CALABRESA + QUEIJO | C7: PÃO | D7: ='Fichas Técnicas - Pães'!G44 -> 2.03391 | E7: ='Fichas Técnicas - Pães'!G45 -> 5.898339 | F7: ='Fichas Técnicas - Pães'!G46 -> 0.34482759 | G7: =IFERROR(E7/D7,0) -> 2.9 | H7: =IF(F7<='Custos & Ponto Equilíbrio'!$B$5,"🟢 Ideal",IF(F7<='Custos & Ponto Equilíbrio'!$B$4,"🟡 Atenção","🔴 Alto")) -> 🟡 Atenção
A8: P003 | B8: 🥖 PÃO RECHEADO PRESUNTO + QUEIJO | C8: PÃO | D8: ='Fichas Técnicas - Pães'!G64 -> 2.04471 | E8: ='Fichas Técnicas - Pães'!G65 -> 5.929659 | F8: ='Fichas Técnicas - Pães'!G66 -> 0.34482759 | G8: =IFERROR(E8/D8,0) -> 2.9 | H8: =IF(F8<='Custos & Ponto Equilíbrio'!$B$5,"🟢 Ideal",IF(F8<='Custos & Ponto Equilíbrio'!$B$4,"🟡 Atenção","🔴 Alto")) -> 🟡 Atenção
A9: P004 | B9: 🥖 PÃO RECHEADO RÚCULA + QUEIJO | C9: PÃO | D9: ='Fichas Técnicas - Pães'!G85 -> 2.41191 | E9: ='Fichas Técnicas - Pães'!G86 -> 6.994539 | F9: ='Fichas Técnicas - Pães'!G87 -> 0.34482759 | G9: =IFERROR(E9/D9,0) -> 2.9 | H9: =IF(F9<='Custos & Ponto Equilíbrio'!$B$5,"🟢 Ideal",IF(F9<='Custos & Ponto Equilíbrio'!$B$4,"🟡 Atenção","🔴 Alto")) -> 🟡 Atenção
A10: ▶ SOBREMESAS GOURMET
A11: S001 | B11: 🍫 MOUSSE DE CHOCOLATE | C11: SOBREMESA | D11: ='Fichas Técnicas - Sobremesas'!G16 -> 3.3696 | E11: ='Fichas Técnicas - Sobremesas'!G17 -> 10.1088 | F11: ='Fichas Técnicas - Sobremesas'!G18 -> 0.33333333 | G11: =IFERROR(E11/D11,0) -> 3 | H11: =IF(F11<='Custos & Ponto Equilíbrio'!$B$5,"🟢 Ideal",IF(F11<='Custos & Ponto Equilíbrio'!$B$4,"🟡 Atenção","🔴 Alto")) -> 🟡 Atenção
A12: S002 | B12: 🥭 MOUSSE DE MARACUJÁ | C12: SOBREMESA | D12: ='Fichas Técnicas - Sobremesas'!G31 -> 2.6136 | E12: ='Fichas Técnicas - Sobremesas'!G32 -> 7.8408 | F12: ='Fichas Técnicas - Sobremesas'!G33 -> 0.33333333 | G12: =IFERROR(E12/D12,0) -> 3 | H12: =IF(F12<='Custos & Ponto Equilíbrio'!$B$5,"🟢 Ideal",IF(F12<='Custos & Ponto Equilíbrio'!$B$4,"🟡 Atenção","🔴 Alto")) -> 🟡 Atenção
A13: S003 | B13: 🍋 MOUSSE DE LIMÃO | C13: SOBREMESA | D13: ='Fichas Técnicas - Sobremesas'!G46 -> 2.3382 | E13: ='Fichas Técnicas - Sobremesas'!G47 -> 7.0146 | F13: ='Fichas Técnicas - Sobremesas'!G48 -> 0.33333333 | G13: =IFERROR(E13/D13,0) -> 3 | H13: =IF(F13<='Custos & Ponto Equilíbrio'!$B$5,"🟢 Ideal",IF(F13<='Custos & Ponto Equilíbrio'!$B$4,"🟡 Atenção","🔴 Alto")) -> 🟡 Atenção
A14: S004 | B14: 🍌 BANOFFEE NO POTE | C14: SOBREMESA | D14: ='Fichas Técnicas - Sobremesas'!G63 -> 3.97575 | E14: ='Fichas Técnicas - Sobremesas'!G64 -> 11.92725 | F14: ='Fichas Técnicas - Sobremesas'!G65 -> 0.33333333 | G14: =IFERROR(E14/D14,0) -> 3 | H14: =IF(F14<='Custos & Ponto Equilíbrio'!$B$5,"🟢 Ideal",IF(F14<='Custos & Ponto Equilíbrio'!$B$4,"🟡 Atenção","🔴 Alto")) -> 🟡 Atenção
A15: S005 | B15: 🍮 PAVÊ NO POTE | C15: SOBREMESA | D15: ='Fichas Técnicas - Sobremesas'!G79 -> 2.7216 | E15: ='Fichas Técnicas - Sobremesas'!G80 -> 8.1648 | F15: ='Fichas Técnicas - Sobremesas'!G81 -> 0.33333333 | G15: =IFERROR(E15/D15,0) -> 3 | H15: =IF(F15<='Custos & Ponto Equilíbrio'!$B$5,"🟢 Ideal",IF(F15<='Custos & Ponto Equilíbrio'!$B$4,"🟡 Atenção","🔴 Alto")) -> 🟡 Atenção
A17: MÉDIA / TOTAL DO CARDÁPIO | D17: =AVERAGE(D6:D9,D11:D15) -> 2.68401 | E17: =AVERAGE(E6:E9,E11:E15) -> 7.950504 | F17: =AVERAGE(F6:F9,F11:F15) -> 0.33844189 | G17: =AVERAGE(G6:G9,G11:G15) -> 2.9555556
A19: Status: 🟢 CMV até a faixa de Atenção (ideal) | 🟡 entre Atenção e Meta (monitorar) | 🔴 acima da Meta (revisar preço ou receita). Preço de venda é sugerido pelo markup da categoria — ajuste manualmente na ficha técnica se praticar outro preço.

Sheet Painel Saúde do Negócio
A1: 📊 PAINEL DE SAÚDE FINANCEIRA | CASA RECHEADA
A3: 🔑 KPIs DO MÊS ATUAL
A4: FATURAMENTO R$ | B4: CMV TOTAL R$ | C4: CMV % | D4: CUSTO FIXO R$ | E4: LUCRO LÍQUIDO R$ | F4: MARGEM %
A5: =B14 -> 0 | B5: =B21 -> 0 | C5: =B22 -> 0 | D5: ='Custos & Ponto Equilíbrio'!B22 -> 396 | E5: =B29 -> -518.5 | F5: =B30 -> 0
A7: 💰 FATURAMENTO POR CANAL
A8: Canal | B8: Mês 1 | C8: Mês 2 | D8: Mês 3 | E8: Mês 4 | F8: Mês 5 | G8: Mês 6
A9: WhatsApp direto | B9: 0 | C9: 0 | D9: 0 | E9: 0 | F9: 0 | G9: 0
A10: Instagram | B10: 0 | C10: 0 | D10: 0 | E10: 0 | F10: 0 | G10: 0
A11: Indicação / boca a boca | B11: 0 | C11: 0 | D11: 0 | E11: 0 | F11: 0 | G11: 0
A12: Eventos / encomendas | B12: 0 | C12: 0 | D12: 0 | E12: 0 | F12: 0 | G12: 0
A13: Outros | B13: 0 | C13: 0 | D13: 0 | E13: 0 | F13: 0 | G13: 0
A14: FATURAMENTO TOTAL | B14: =SUM(B9:B13) -> 0 | C14: =SUM(C9:C13) -> 0 | D14: =SUM(D9:D13) -> 0 | E14: =SUM(E9:E13) -> 0 | F14: =SUM(F9:F13) -> 0 | G14: =SUM(G9:G13) -> 0
A16: 📦 CMV REAL POR CATEGORIA
A17: Categoria CMV | B17: Mês 1 | C17: Mês 2 | D17: Mês 3 | E17: Mês 4 | F17: Mês 5 | G17: Mês 6
A18: CMV Pães Recheados | B18: 0 | C18: 0 | D18: 0 | E18: 0 | F18: 0 | G18: 0
A19: CMV Sobremesas Gourmet | B19: 0 | C19: 0 | D19: 0 | E19: 0 | F19: 0 | G19: 0
A20: CMV Embalagens/Etiquetas | B20: 0 | C20: 0 | D20: 0 | E20: 0 | F20: 0 | G20: 0
A21: CMV TOTAL | B21: =SUM(B18:B20) -> 0 | C21: =SUM(C18:C20) -> 0 | D21: =SUM(D18:D20) -> 0 | E21: =SUM(E18:E20) -> 0 | F21: =SUM(F18:F20) -> 0 | G21: =SUM(G18:G20) -> 0
A22: CMV % DO FATURAMENTO | B22: =IFERROR(B21/B14,0) -> 0 | C22: =IFERROR(C21/C14,0) -> 0 | D22: =IFERROR(D21/D14,0) -> 0 | E22: =IFERROR(E21/E14,0) -> 0 | F22: =IFERROR(F21/F14,0) -> 0 | G22: =IFERROR(G21/G14,0) -> 0
A24: 📈 RESULTADO MENSAL (Mês 1 como referência)
A25: Faturamento Total (Mês 1) | B25: =B14 -> 0
A26: (-) CMV Total (Mês 1) | B26: =-B21 -> 0
A27: (-) Custo Fixo Médio Mensal | B27: =-'Custos & Ponto Equilíbrio'!B22 -> -396
A28: (-) Outros Custos Variáveis (limpeza, gás extra etc.) | B28: =-('Custos & Ponto Equilíbrio'!I32-'Custos & Ponto Equilíbrio'!I26-'Custos & Ponto Equilíbrio'!I27-'Custos & Ponto Equilíbrio'!I28) -> -122.5
A29: LUCRO LÍQUIDO R$ (Mês 1) | B29: =B25+B26+B27+B28 -> -518.5
A30: MARGEM LÍQUIDA % (Mês 1) | B30: =IFERROR(B29/B25,0) -> 0
A32: =IF(B14=0,"",IF(B22>'Custos & Ponto Equilíbrio'!$B$4,"🔴 CMV CRÍTICO: "&TEXT(B22,"0.0%")&" — ACIMA DA META DE "&TEXT('Custos & Ponto Equilíbrio'!$B$4,"0%")&" ▶ REVISE PREÇOS OU RECEITAS",IF(B22>='Custos & Ponto Equilíbrio'!$B$5,"🟡 CMV EM ATENÇÃO: "&TEXT(B22,"0.0%")&" — Faixa de risco — Meta: "&TEXT('Custos & Ponto Equilíbrio'!$B$4,"0%"),"🟢 CMV EXCELENTE: "&TEXT(B22,"0.0%")&" — Abaixo de "&TEXT('Custos & Ponto Equilíbrio'!$B$5,"0%")&" — LUCRATIVIDADE ÓTIMA")))
A34: 🔴 CAPITAL & INVESTIMENTO INICIAL
A35: Reserva de Capital de Giro Necessária (R$) | B35: ='Custos & Ponto Equilíbrio'!B50 -> 5388
A36: Investimento Inicial Total Estimado — Mín. (R$) | B36: ='Custos & Ponto Equilíbrio'!B66 -> 11278
A37: 🔴 TOTAL NECESSÁRIO ANTES DE ABRIR (Giro + CAPEX) | B37: ='Custos & Ponto Equilíbrio'!B50+'Custos & Ponto Equilíbrio'!B66 -> 16666
A39: ✏️ Células AZUIS = editáveis (preencha com o real de cada mês) | PRETO/GOLD = fórmulas | CMV: 🟢 ≤ Atenção · 🟡 entre Atenção e Meta · 🔴 acima da Meta
